FigStats/__init__.py
FigStats/word.py
mrpythonhello-0.0.1.dist-info/LICENSE
mrpythonhello-0.0.1.dist-info/METADATA
mrpythonhello-0.0.1.dist-info/WHEEL
mrpythonhello-0.0.1.dist-info/top_level.txt
mrpythonhello-0.0.1.dist-info/RECORD
