Metadata-Version: 2.1
Name: mrpythonhello
Version: 0.0.1
Summary: mrpythonlib
Author: Bilal Ahmad
Author-email: bilalahmad176176@gmail.com
Keywords: python,mr python,area of figs,area,developergautam
Classifier: Development Status :: 1 - Planning
Classifier: Intended Audience :: Developers
Classifier: Programming Language :: Python :: 3
Classifier: Operating System :: Unix
Classifier: Operating System :: MacOS :: MacOS X
Classifier: Operating System :: Microsoft :: Windows
License-File: LICENSE
